{
	"$schema": "https://schemas.wp.org/trunk/block.json",
	"apiVersion": 2,
	"name": "shp/gantrisch-adb-offer-condition",
	"title": "ADB Offer Condition",
	"category": "media",
	"icon": "database",
	"description": "The actual content will be loaded dynamically by passing an offer ID to the page on which this block has been placed.",
	"keywords": ["offer", "angebot", "route", "condition"],
	"textdomain": "shp_gantrisch_adb",
	"attributes": {
		"align": {
			"type": "string"
		},
		"prefix": {
			"type": "string",
			"default": "Routenzustand:"
		}
	},
	"supports": {
		"align": false,
		"html": false
	},
	"editorScript": "file:./assets/dist/scripts/editor.js",
	"style": [
		"file:./assets/dist/styles/shared/index.min.css",
		"shp-gantrisch-adb-offer-condition"
	],
	"render": "file:./render.php"
}
